odoo10_addon_medical_procedure-10.0.1.0.0-py2.7-nspkg.pth
odoo/addons/medical_procedure/README.rst
odoo/addons/medical_procedure/__init__.py
odoo/addons/medical_procedure/__manifest__.py
odoo/addons/medical_procedure/demo/medical_procedure.xml
odoo/addons/medical_procedure/models/__init__.py
odoo/addons/medical_procedure/models/medical_procedure.py
odoo/addons/medical_procedure/security/ir.model.access.csv
odoo/addons/medical_procedure/views/medical_procedure.xml
odoo10_addon_medical_procedure-10.0.1.0.0.dist-info/DESCRIPTION.rst
odoo10_addon_medical_procedure-10.0.1.0.0.dist-info/METADATA
odoo10_addon_medical_procedure-10.0.1.0.0.dist-info/RECORD
odoo10_addon_medical_procedure-10.0.1.0.0.dist-info/WHEEL
odoo10_addon_medical_procedure-10.0.1.0.0.dist-info/metadata.json
odoo10_addon_medical_procedure-10.0.1.0.0.dist-info/namespace_packages.txt
odoo10_addon_medical_procedure-10.0.1.0.0.dist-info/top_level.txt
